flask_vises/__init__.py
flask_vises/config.py
flask_vises/deploy.py
flask_vises/flask_celery.py
flask_vises/flask_redis.py
flask_vises/password.py
flask_vises/testing.py
flask_vises/database/__init__.py
flask_vises/database/models.py
Flask_Vises-2.1.4.dist-info/LICENSE
Flask_Vises-2.1.4.dist-info/METADATA
Flask_Vises-2.1.4.dist-info/WHEEL
Flask_Vises-2.1.4.dist-info/top_level.txt
Flask_Vises-2.1.4.dist-info/RECORD
