Metadata-Version: 2.1
Name: Flask-Vises
Version: 2.1.4
Summary: A Flask scaffold library
Home-page: https://github.com/rexzhang/flask-vises
Author: Rex Zhang
Author-email: rex.zhang@gmail.com
License: UNKNOWN
Project-URL: Bug Reports, https://github.com/rexzhang/flask-vises/issues
Project-URL: Source, https://github.com/rexzhang/flask-vises/
Keywords: Flask Flask-SQLAlchemy Flask-Testing redis celery
Platform: UNKNOWN
Classifier: Development Status :: 4 - Beta
Classifier: Intended Audience :: Developers
Classifier: License :: OSI Approved :: MIT License
Classifier: Programming Language :: Python :: 3.4
Classifier: Programming Language :: Python :: 3.5
Classifier: Programming Language :: Python :: 3.6
Classifier: Programming Language :: Python :: 3.7
Requires-Dist: Flask (>=1.0.2)
